pyapm/__init__.py
pyapm/__main__.py
pyapm/classes/__init__.py
pyapm/classes/boundedge.py
pyapm/classes/dirichletpoly.py
pyapm/classes/edge.py
pyapm/classes/grid.py
pyapm/classes/horseshoe.py
pyapm/classes/horseshoedoublet.py
pyapm/classes/horseshoevortex2d.py
pyapm/classes/panel.py
pyapm/classes/panelcontrol.py
pyapm/classes/panelfunction.py
pyapm/classes/panelprofile.py
pyapm/classes/panelresult.py
pyapm/classes/panelsection.py
pyapm/classes/panelsheet.py
pyapm/classes/panelstrip.py
pyapm/classes/panelsurface.py
pyapm/classes/panelsystem.py
pyapm/classes/paneltrim.py
pyapm/classes/poly.py
pyapm/classes/surfaceload.py
pyapm/classes/surfacestructure.py
pyapm/classes/trailingedge.py
pyapm/outputs/__init__.py
pyapm/outputs/k3d.py
pyapm/outputs/md.py
pyapm/outputs/msh.py
pyapm/tools/__init__.py
pyapm/tools/airfoil.py
pyapm/tools/cupy.py
pyapm/tools/functions.py
pyapm/tools/mass.py
pyapm/tools/naca4.py
pyapm/tools/naca6series.py
pyapm/tools/numpy.py
pyapm/tools/points.py
pyapm/tools/polyfoil.py
pyapm/tools/rigidbody.py
pyapm/tools/trim.py
pyapm-0.0.3.dist-info/licenses/LICENSE
pyapm-0.0.3.dist-info/METADATA
pyapm-0.0.3.dist-info/WHEEL
pyapm-0.0.3.dist-info/entry_points.txt
pyapm-0.0.3.dist-info/top_level.txt
pyapm-0.0.3.dist-info/RECORD
